{
  "mongodb": {
    "database": "authorization_db",
    "host": "localhost",
    "port": 27017
  },
  "logger": {
    "name": "API-Gateway-DEV",
    "level": "debug",
    "type": "console",
    "toFile": false,
    "stackdriver": false
  },
  "server": {
    "port": 9050,
    "publicUrl": "http://authorization.dev:9000",
    "internalUrl": "http://localhost:9050",
    "cookie": {
      "domain": "authorization.dev"
    },
    "sessionKey": "authorization-key"
  },
  "service": {
    "name": "Authorization"
  },
  "application": {
    "name": "RW API",
    "logo": "http://www.wri.org/sites/all/themes/wri/images/logo.png",
    "principalColor": "#f1b319",
    "sendNotifications": false,
    "emailSenderName": "RW API"
  },
  "jwt": {
    "token": ""
  }
}
